setup.cfg
setup.py
name_me.egg-info/PKG-INFO
name_me.egg-info/SOURCES.txt
name_me.egg-info/dependency_links.txt
name_me.egg-info/top_level.txt
nameme/__init__.py
nameme/adjectives.py
nameme/nouns.py