Metadata-Version: 1.0
Name: name-me
Version: 0.1.0
Summary: Generate random strings you can actually remember
Home-page: https://github.com/Dinoshauer/name-me
Author: Kasper Jacobsen
Author-email: k@mackwerk.dk
License: MIT
Platform: UNKNOWN
